miriton/__init__.py
miriton/demo.py
miriton-0.0.1.dist-info/METADATA
miriton-0.0.1.dist-info/WHEEL
miriton-0.0.1.dist-info/top_level.txt
miriton-0.0.1.dist-info/RECORD
